{
  "income-basics": {
    "title": "Розуміння вашого доходу",
    "description": "Валова та чиста зарплата, сума на руки, а також як переводити дохід між погодинними, місячними та річними показниками."
  },
  "income-tax": {
    "title": "Як працює податок на доходи",
    "description": "Податкові ставки, відрахування, соціальні внески та те, як податок на доходи впливає на вашу зарплату на руки в різних країнах."
  },
  "salary-career": {
    "title": "Зарплата, робота та планування фінансів",
    "description": "Оцінюйте свою оплату праці, порівнюйте пропозиції роботи, зважуйте вартість життя та розбирайтеся в різниці між доходом фрилансера та найманого працівника."
  }
}
